compare_dicts_lib/__init__.py
compare_dicts_lib/compare_dicts.py
compare_dicts_lib-0.2.0.dist-info/LICENSE
compare_dicts_lib-0.2.0.dist-info/METADATA
compare_dicts_lib-0.2.0.dist-info/WHEEL
compare_dicts_lib-0.2.0.dist-info/top_level.txt
compare_dicts_lib-0.2.0.dist-info/RECORD
