Metadata-Version: 2.2
Name: compare-dicts-lib
Version: 0.2.0
Summary: A lightweight Python library for comparing two dictionaries and getting only the differences.
Author-email: Super Gabian <supergabian13@gmail.com>
License: MIT License
Project-URL: Homepage, https://github.com/SuperGabian/compare_dicts_lib
Project-URL: Repository, https://github.com/SuperGabian/compare_dicts_lib
Requires-Python: >=3.7
License-File: LICENSE
